AxisLabeling.py
axislabeling-0.0.2.dist-info/LICENSE
axislabeling-0.0.2.dist-info/METADATA
axislabeling-0.0.2.dist-info/WHEEL
axislabeling-0.0.2.dist-info/top_level.txt
axislabeling-0.0.2.dist-info/RECORD
