Metadata-Version: 2.2
Name: AxisLabeling
Version: 0.0.2
Summary: Implementation of axis-labeling algorithms
Home-page: https://github.com/StatguyUser/AxisLabeling
Download-URL: https://github.com/StatguyUser/AxisLabeling.git
Author: StatguyUser
License-File: LICENSE
Requires-Dist: numpy
Dynamic: author
Dynamic: description
Dynamic: description-content-type
Dynamic: download-url
Dynamic: home-page
Dynamic: requires-dist
Dynamic: summary
